Workbook

Sheet weerhouden waarde
A1: [NAAM VENNOOTSCHAP]
A2: [straat + nummer]
A3: [postcode + gemeente]
A4: ON. [ondernemingsnummer]
A6: Toestand op [afsluitdatum] (afsluitdatum)
A8: WEERHOUDEN WAARDE
A10: Rekening houdende met de aard en de activiteiten van de vennootschap, zijnde [omschrijving activiteit], worden ter bepaling van de waarde van de aandelen van de in rand vermelde vennootschap, navolgende methoden toegepast :
A15: - Een substantiële waardebepaling
A16: - Een rendementswaarde berekening
A17: - Een berekening naar de waarde op basis van de EBITDA (marktwaarde)
A18: - Een berekening naar de waarde op basis van de DCF-methode
A20: De substantiële waarde wordt bekomen op basis van het eigen vermogen van de vennootschap. De eigen vermogenswaarde wordt gecorrigeerd met de latente min- en/of meerwaarden die op de activa en passiva aanwezig zijn. Hieraan wordt de waarde van de goodwill, berekend op basis van de verwachte recurrente inkomsten- en uitgavenstromen, toegevoegd.
... A68: van de in rand vermelde vennootschap weerhouden worden :
A75: Substantiële waarde | B75: ='substantiële waarde'!C14 -> 0 | C75: x 1/3 | D75: =B75*1/3 -> 0
A76: Rendementswaarde | B76: =Rendementswaarde!C15 -> 0 | C76: x 1/3 | D76: =B76*1/3 -> 0
A77: Marktwaarde (EBITDA) | B77: ='Marktwaarde '!D27 -> 0 | C77: x 1/3 | D77: =B77*1/3 -> 0
A78: DCF waarde | B78: 0 | C78: x 1/4 | D78: =B78*1/4 -> 0
A80: ="Waarde 100% aandelen "&A1 -> Waarde 100% aandelen [NAAM VENNOOTSCHAP] | D80: =SUM(D75:D77) -> 0
A82: afgerond = | D82: =ROUND(D80,-3) -> 0
A91: 3. Een voorbehoud omtrent de bodemtoestand van het onroerend en de eventuele aanwezigheid van asbest,
A92: aangezien ons hieromtrent geen verdere informatie beschikbaar is.
A95: PM
A97: 1. Er worden verondersteld geen hangende geschillen (met overheidsdiensten, fiscus, derden,…) e.d. te zijn met een van materiële aarde zijnde negatieve impact voor de vennootschap.
A100: 2. De gebruikte historische cijfers zijn geen geauditeerde cijfers.
A102: 3. Er wordt geen rekening gehouden met de eigen vermogensevolutie na [afsluitdatum].
B159: (6) en (7) financiële opbrengsten/kosten op overtollige activa/passiva worden hier geannuleerd, net als positieve/negatieve wisselkoersverschillen

Sheet Swot
B1: ="SWOT analyse voor bepaling waarde aandelen "&'weerhouden waarde'!A1 -> SWOT analyse voor bepaling waarde aandelen [NAAM VENNOOTSCHAP]
B4: STERKTES | D4: ZWAKTES
B18: OPPORTUNITEITEN | D18: BEDREIGINGEN

Sheet substantiële waarde
A1: ='weerhouden waarde'!A1 -> [NAAM VENNOOTSCHAP]
A4: ='weerhouden waarde'!A6 -> Toestand op [afsluitdatum] (afsluitdatum)
A7: SUBSTANTIËLE WAARDE
A10: gecorrigeerd eigen vermogen | B10: =ROUND('gecorrigeerd eigen vermogen'!E44,-3) -> 0
A11: goodwill | B11: =Goodwill!D22 -> 0
A14: Substantiële waarde | C14: =B11+B10 -> 0

Sheet gecorrigeerd eigen vermogen
A1: ='weerhouden waarde'!A1 -> [NAAM VENNOOTSCHAP]
A4: ='weerhouden waarde'!A6 -> Toestand op [afsluitdatum] (afsluitdatum)
A7: GECORRIGEERD EIGEN VERMOGEN
A9: eigen vermogen | E9: =SUM(D11:D13) -> 0
A11: Beschikbare inbreng buiten kapitaal
A12: Beschikbare reserves - liquidatiereserves
A13: Overgedragen winst
A15: correcties op eigen vermogen | E15: =SUM(D17:D19) -> 0
A17: latente meerwaarde onroerende goederen (zie detail meerw. MVA) | D17: =MVA!M33 -> 0
A18: latente meerwaarde roerende goederen (zie detail meerw. MVA) | D18: =MVA!M114 -> 0
A19: latente minderwaarde handelsvorderingen (3) | D19: 0
A21: latentie vennootschapsbelasting | E21: =-D26 -> 0
A24: =A18 -> latente meerwaarde roerende goederen (zie detail meerw. MVA) | D24: =D18 -> 0
D25: =SUM(D24:D24) -> 0
B26: (1) | C26: =D60 -> 0.19024739 | D26: =D25*C26 -> 0
A28: =A19 -> latente minderwaarde handelsvorderingen (3) | D28: =D19 -> 0
D29: =D28 -> 0
C30: 0.125 | D30: =D29*C30 -> 0
A33: Latentie liquidatiebelasting op gecorr EV - kapitaal | E33: =-D39 -> 0
A34: =A12 -> Beschikbare reserves - liquidatiereserves | D34: =D12 -> 0
A35: =A13 -> Overgedragen winst | D35: =D13 -> 0
A36: correcties op eigen vermogen | D36: =E15 -> 0
A37: belastingslatentie op correcties eigen vermogen | D37: =E21 -> 0
D38: =SUM(D34:D37) -> 0
B39: (2) | C39: 0 | D39: =D38*C39 -> 0
A44: Gecorrigeerd eigen vermogen | E44: =SUM(E7:E42) -> 0
A47: (1) : Inbreng | B47: Inbreng [datum oprichting / omschrijving]
C48: =SUM(C47:C47) -> 0 | D48: =SUM(D47:D47) -> 0
A50: (1) : latentie vennootschapsbelasting :
A51: Het tarief van de latente vennootschapsbelasting wordt berekend uitgaande van het vigerend tarief in de vennootschapsbelasting (ad 25%) waarbij een actualisatie wordt doorgevoerd voor een periode van 10 jaar aan een jaarlijkse verdisconteringsfactor dewelke overeenstemt met de gemiddelde OLO van de laatste 20 jaar
D56: 10 jaar
B57: - toepasselijk tarief vennootschapsbelasting | D57: 0.25
B58: - gemiddelde OLO rentevoet van laatste 20 jaar | D58: =+OLO!G49 -> 0.02769
B59: - toepasselijke verdisconteringscoëfficiënt | D59: =1/(1+D58)^10 -> 0.76098955
B60: - tarief latente vennootschapsbelasting | D60: =D57*D59 -> 0.19024739
A62: (2) : latentie liquidatiebelastingen :
A63: We gaan in onderhavige waardering uit van het scenario dat de aandelen in de toekomst worden aangehouden door een holdingvennootschap. Aldus wordt geen latente liquidatiebelasting weerhouden.
A66: (3) : latentie minderwaarde handelsvorderingen :
A67: Op basis van het detail van de openstaande klanten d.d. [datum] [besluit over achterstallige saldi]. We weerhouden aldus [geen] latente minderwaarde op de openstaande handelsvorderingen per [afsluitdatum].
A112: (4): Nihil wegens vennootschapsaandeelhouders

Sheet MVA
A1: ='weerhouden waarde'!A1 -> [NAAM VENNOOTSCHAP]
A4: ='weerhouden waarde'!A6 -> Toestand op [afsluitdatum] (afsluitdatum)
B6: WAARDERING MATERIËLE VASTE ACTIVA
A9: datum | B9: jaar | C9: omschrijving | D9: AW | E9: restwaarde | F9: af te schrijven | G9: # jaar | H9: afgeschr. | I9: afschrijvingen | J9: berekende BW | K9: weerhouden w. | L9: BW klant | M9: latente mw | N9: Vervangingsinvest.
C11: ONROERENDE GOEDEREN
C13: Terreinen en gebouwen
C15: Bedrijfspand - [adres]
D30: =SUM(D16:D29) -> 0 | K30: =IF(D43="",L30,ROUND(D43,-3)) -> 0 | M30: =K30-L30 -> 0
C33: TOTAAL | D33: =D30 -> 0 | J33: (1) | K33: =K30 -> 0 | L33: =L30 -> 0 | M33: =K33-L33 -> 0
L35: Afgerond | M35: =ROUND(M33,-3) -> 0
B36: (1) | C36: Raming actuele venale waarde onroerend goed
C38: Marktwaarde cfr. schattingsverslag [schatter] | E38: (marktwaarde - vrij op naam)
C39: d.d. [datum schattingsverslag]
C41: Indexatie t.o.v. datum schattingsverslag (leeg = geen indexatie)
C43: Geindexeerde marktwaarde | D43: =IF(D38="","",D38*IF(D41="",1,D41))
C46: ROERENDE GOEDEREN
C48: Computers/hardware (#240100)
C49: 5 jaar met restwaarde = 0%
E50: =D50*0 -> 0 | F50: =D50-E50 -> 0 | G50: 5 | H50: =IF(B50="",G50,IF($H$7-B50>G50,G50,$H$7-B50)) -> 5 | I50: =F50/G50*H50 -> 0 | J50: =D50-I50 -> 0 | K50: =J50 -> 0
E51: =D51*0 -> 0 | F51: =D51-E51 -> 0 | G51: 5 | H51: =IF(B51="",G51,IF($H$7-B51>G51,G51,$H$7-B51)) -> 5 | I51: =F51/G51*H51 -> 0 | J51: =D51-I51 -> 0 | K51: =J51 -> 0
E52: =D52*0 -> 0 | F52: =D52-E52 -> 0 | G52: 5 | H52: =IF(B52="",G52,IF($H$7-B52>G52,G52,$H$7-B52)) -> 5 | I52: =F52/G52*H52 -> 0 | J52: =D52-I52 -> 0 | K52: =J52 -> 0
E53: =D53*0 -> 0 | F53: =D53-E53 -> 0 | G53: 5 | H53: =IF(B53="",G53,IF($H$7-B53>G53,G53,$H$7-B53)) -> 5 | I53: =F53/G53*H53 -> 0 | J53: =D53-I53 -> 0 | K53: =J53 -> 0
E54: =D54*0 -> 0 | F54: =D54-E54 -> 0 | G54: 5 | H54: =IF(B54="",G54,IF($H$7-B54>G54,G54,$H$7-B54)) -> 5 | I54: =F54/G54*H54 -> 0 | J54: =D54-I54 -> 0 | K54: =J54 -> 0
D55: =SUM(D50:D54) -> 0 | E55: =SUM(E50:E54) -> 0 | F55: =SUM(F50:F54) -> 0 | I55: =SUM(I50:I54) -> 0 | J55: =SUM(J50:J54) -> 0 | K55: =SUM(K50:K54) -> 0 | M55: =K55-L55 -> 0 | N55: =F55/G50 -> 0
C58: Installaties, machines en uitrusting (#230000)
C59: 7 jaar met een restwaarde van 10% (voor investeringen na 2018)
E60: =D60*IF(B60>2018,10%,0) -> 0 | F60: =D60-E60 -> 0 | G60: 7 | H60: =IF(B60="",G60,IF($H$7-B60>G60,G60,$H$7-B60)) -> 7 | I60: =F60/G60*H60 -> 0 | J60: =D60-I60 -> 0 | K60: =J60 -> 0
E61: =D61*IF(B61>2018,10%,0) -> 0 | F61: =D61-E61 -> 0 | G61: 7 | H61: =IF(B61="",G61,IF($H$7-B61>G61,G61,$H$7-B61)) -> 7 | I61: =F61/G61*H61 -> 0 | J61: =D61-I61 -> 0 | K61: =J61 -> 0
E62: =D62*IF(B62>2018,10%,0) -> 0 | F62: =D62-E62 -> 0 | G62: 7 | H62: =IF(B62="",G62,IF($H$7-B62>G62,G62,$H$7-B62)) -> 7 | I62: =F62/G62*H62 -> 0 | J62: =D62-I62 -> 0 | K62: =J62 -> 0
E63: =D63*IF(B63>2018,10%,0) -> 0 | F63: =D63-E63 -> 0 | G63: 7 | H63: =IF(B63="",G63,IF($H$7-B63>G63,G63,$H$7-B63)) -> 7 | I63: =F63/G63*H63 -> 0 | J63: =D63-I63 -> 0 | K63: =J63 -> 0
E64: =D64*IF(B64>2018,10%,0) -> 0 | F64: =D64-E64 -> 0 | G64: 7 | H64: =IF(B64="",G64,IF($H$7-B64>G64,G64,$H$7-B64)) -> 7 | I64: =F64/G64*H64 -> 0 | J64: =D64-I64 -> 0 | K64: =J64 -> 0
E65: =D65*IF(B65>2018,10%,0) -> 0 | F65: =D65-E65 -> 0 | G65: 7 | H65: =IF(B65="",G65,IF($H$7-B65>G65,G65,$H$7-B65)) -> 7 | I65: =F65/G65*H65 -> 0 | J65: =D65-I65 -> 0 | K65: =J65 -> 0
E66: =D66*IF(B66>2018,10%,0) -> 0 | F66: =D66-E66 -> 0 | G66: 7 | H66: =IF(B66="",G66,IF($H$7-B66>G66,G66,$H$7-B66)) -> 7 | I66: =F66/G66*H66 -> 0 | J66: =D66-I66 -> 0 | K66: =J66 -> 0
E67: =D67*IF(B67>2018,10%,0) -> 0 | F67: =D67-E67 -> 0 | G67: 7 | H67: =IF(B67="",G67,IF($H$7-B67>G67,G67,$H$7-B67)) -> 7 | I67: =F67/G67*H67 -> 0 | J67: =D67-I67 -> 0 | K67: =J67 -> 0
E68: =D68*IF(B68>2018,10%,0) -> 0 | F68: =D68-E68 -> 0 | G68: 7 | H68: =IF(B68="",G68,IF($H$7-B68>G68,G68,$H$7-B68)) -> 7 | I68: =F68/G68*H68 -> 0 | J68: =D68-I68 -> 0 | K68: =J68 -> 0
E69: =D69*IF(B69>2018,10%,0) -> 0 | F69: =D69-E69 -> 0 | G69: 7 | H69: =IF(B69="",G69,IF($H$7-B69>G69,G69,$H$7-B69)) -> 7 | I69: =F69/G69*H69 -> 0 | J69: =D69-I69 -> 0 | K69: =J69 -> 0
E70: =D70*IF(B70>2018,10%,0) -> 0 | F70: =D70-E70 -> 0 | G70: 7 | H70: =IF(B70="",G70,IF($H$7-B70>G70,G70,$H$7-B70)) -> 7 | I70: =F70/G70*H70 -> 0 | J70: =D70-I70 -> 0 | K70: =J70 -> 0
E71: =D71*IF(B71>2018,10%,0) -> 0 | F71: =D71-E71 -> 0 | G71: 7 | H71: =IF(B71="",G71,IF($H$7-B71>G71,G71,$H$7-B71)) -> 7 | I71: =F71/G71*H71 -> 0 | J71: =D71-I71 -> 0 | K71: =J71 -> 0
... E79: =D79*IF(B79>2018,10%,0) -> 0 | F79: =D79-E79 -> 0 | G79: 7 | H79: =IF(B79="",G79,IF($H$7-B79>G79,G79,$H$7-B79)) -> 7 | I79: =F79/G79*H79 -> 0 | J79: =D79-I79 -> 0 | K79: =J79 -> 0
D80: =SUM(D60:D79) -> 0 | E80: =SUM(E60:E79) -> 0 | F80: =SUM(F60:F79) -> 0 | I80: =SUM(I60:I79) -> 0 | J80: =SUM(J60:J79) -> 0 | K80: =SUM(K60:K79) -> 0 | M80: =K80-L80 -> 0 | N80: =F80/G60 -> 0
C82: Meubilair (#240000)
C83: 7 jaar met een restwaarde van 10% (voor investeringen na 2018)
E84: =D84*IF(B84>2018,10%,0) -> 0 | F84: =D84-E84 -> 0 | G84: 7 | H84: =IF(B84="",G84,IF($H$7-B84>G84,G84,$H$7-B84)) -> 7 | I84: =F84/G84*H84 -> 0 | J84: =D84-I84 -> 0 | K84: =J84 -> 0
E85: =D85*IF(B85>2018,10%,0) -> 0 | F85: =D85-E85 -> 0 | G85: 7 | H85: =IF(B85="",G85,IF($H$7-B85>G85,G85,$H$7-B85)) -> 7 | I85: =F85/G85*H85 -> 0 | J85: =D85-I85 -> 0 | K85: =J85 -> 0
E86: =D86*IF(B86>2018,10%,0) -> 0 | F86: =D86-E86 -> 0 | G86: 7 | H86: =IF(B86="",G86,IF($H$7-B86>G86,G86,$H$7-B86)) -> 7 | I86: =F86/G86*H86 -> 0 | J86: =D86-I86 -> 0 | K86: =J86 -> 0
E87: =D87*IF(B87>2018,10%,0) -> 0 | F87: =D87-E87 -> 0 | G87: 7 | H87: =IF(B87="",G87,IF($H$7-B87>G87,G87,$H$7-B87)) -> 7 | I87: =F87/G87*H87 -> 0 | J87: =D87-I87 -> 0 | K87: =J87 -> 0
E88: =D88*IF(B88>2018,10%,0) -> 0 | F88: =D88-E88 -> 0 | G88: 7 | H88: =IF(B88="",G88,IF($H$7-B88>G88,G88,$H$7-B88)) -> 7 | I88: =F88/G88*H88 -> 0 | J88: =D88-I88 -> 0 | K88: =J88 -> 0
E89: =D89*IF(B89>2018,10%,0) -> 0 | F89: =D89-E89 -> 0 | G89: 7 | H89: =IF(B89="",G89,IF($H$7-B89>G89,G89,$H$7-B89)) -> 7 | I89: =F89/G89*H89 -> 0 | J89: =D89-I89 -> 0 | K89: =J89 -> 0
E90: =D90*IF(B90>2018,10%,0) -> 0 | F90: =D90-E90 -> 0 | G90: 7 | H90: =IF(B90="",G90,IF($H$7-B90>G90,G90,$H$7-B90)) -> 7 | I90: =F90/G90*H90 -> 0 | J90: =D90-I90 -> 0 | K90: =J90 -> 0
E91: =D91*IF(B91>2018,10%,0) -> 0 | F91: =D91-E91 -> 0 | G91: 7 | H91: =IF(B91="",G91,IF($H$7-B91>G91,G91,$H$7-B91)) -> 7 | I91: =F91/G91*H91 -> 0 | J91: =D91-I91 -> 0 | K91: =J91 -> 0
D92: =SUM(D84:D91) -> 0 | E92: =SUM(E84:E91) -> 0 | F92: =SUM(F84:F91) -> 0 | I92: =SUM(I84:I91) -> 0 | J92: =SUM(J84:J91) -> 0 | K92: =SUM(K84:K91) -> 0 | M92: =K92-L92 -> 0 | N92: =F92/G84 -> 0
C94: Rollend materieel (#241000)
C95: 10 jaar en 10% restwaarde
E96: =D96*10% -> 0 | F96: =D96-E96 -> 0 | G96: 10 | H96: =IF(B96="",G96,IF($H$7-B96>G96,G96,$H$7-B96)) -> 10 | I96: =F96/G96*H96 -> 0 | J96: =D96-I96 -> 0 | K96: =J96 -> 0
E97: =D97*10% -> 0 | F97: =D97-E97 -> 0 | G97: 10 | H97: =IF(B97="",G97,IF($H$7-B97>G97,G97,$H$7-B97)) -> 10 | I97: =F97/G97*H97 -> 0 | J97: =D97-I97 -> 0 | K97: =J97 -> 0
E98: =D98*10% -> 0 | F98: =D98-E98 -> 0 | G98: 10 | H98: =IF(B98="",G98,IF($H$7-B98>G98,G98,$H$7-B98)) -> 10 | I98: =F98/G98*H98 -> 0 | J98: =D98-I98 -> 0 | K98: =J98 -> 0
D99: =SUM(D96:D98) -> 0 | E99: =SUM(E96:E98) -> 0 | F99: =SUM(F96:F98) -> 0 | I99: =SUM(I96:I98) -> 0 | J99: =SUM(J96:J98) -> 0 | K99: =SUM(K96:K98) -> 0 | M99: =K99-L99 -> 0 | N99: =F99/G96 -> 0
C101: Inrichting / huur gebouwen (#232000 / #264000)
C102: 15 jaar zonder restwaarde
E103: =D103*0 -> 0 | F103: =D103-E103 -> 0 | G103: 15 | H103: =IF(B103="",G103,IF($H$7-B103>G103,G103,$H$7-B103)) -> 15 | I103: =F103/G103*H103 -> 0 | J103: =D103-I103 -> 0 | K103: =J103 -> 0
E104: =D104*0 -> 0 | F104: =D104-E104 -> 0 | G104: 15 | H104: =IF(B104="",G104,IF($H$7-B104>G104,G104,$H$7-B104)) -> 15 | I104: =F104/G104*H104 -> 0 | J104: =D104-I104 -> 0 | K104: =J104 -> 0
E105: =D105*0 -> 0 | F105: =D105-E105 -> 0 | G105: 15 | H105: =IF(B105="",G105,IF($H$7-B105>G105,G105,$H$7-B105)) -> 15 | I105: =F105/G105*H105 -> 0 | J105: =D105-I105 -> 0 | K105: =J105 -> 0
E106: =D106*0 -> 0 | F106: =D106-E106 -> 0 | G106: 15 | H106: =IF(B106="",G106,IF($H$7-B106>G106,G106,$H$7-B106)) -> 15 | I106: =F106/G106*H106 -> 0 | J106: =D106-I106 -> 0 | K106: =J106 -> 0
E107: =D107*0 -> 0 | F107: =D107-E107 -> 0 | G107: 15 | H107: =IF(B107="",G107,IF($H$7-B107>G107,G107,$H$7-B107)) -> 15 | I107: =F107/G107*H107 -> 0 | J107: =D107-I107 -> 0 | K107: =J107 -> 0
E108: =D108*0 -> 0 | F108: =D108-E108 -> 0 | G108: 15 | H108: =IF(B108="",G108,IF($H$7-B108>G108,G108,$H$7-B108)) -> 15 | I108: =F108/G108*H108 -> 0 | J108: =D108-I108 -> 0 | K108: =J108 -> 0
E109: =D109*0 -> 0 | F109: =D109-E109 -> 0 | G109: 15 | H109: =IF(B109="",G109,IF($H$7-B109>G109,G109,$H$7-B109)) -> 15 | I109: =F109/G109*H109 -> 0 | J109: =D109-I109 -> 0 | K109: =J109 -> 0
D110: =SUM(D103:D109) -> 0 | E110: =SUM(E103:E109) -> 0 | F110: =SUM(F103:F109) -> 0 | I110: =SUM(I103:I109) -> 0 | J110: =SUM(J103:J109) -> 0 | K110: =SUM(K103:K109) -> 0 | M110: =K110-L110 -> 0 | N110: =F110/G103 -> 0
C112: TOTAAL MVA | D112: =D55+D80+D92+D99+D110 -> 0 | E112: =E55+E80+E92+E99+E110 -> 0 | F112: =F55+F80+F92+F99+F110 -> 0 | I112: =I55+I80+I92+I99+I110 -> 0 | J112: =J55+J80+J92+J99+J110 -> 0 | K112: =K55+K80+K92+K99+K110 -> 0 | L112: =L55+L80+L92+L99+L110 -> 0 | M112: =M55+M80+M92+M99+M110 -> 0 | N112: =N55+N80+N92+N99+N110 -> 0
L114: Afgerond | M114: =ROUND(M112,-3) -> 0
K117: Controle :
C118: Immateriële vaste activa (afschrijvingstabel) | K118: Totaal NBW | L118: =L112+L33 -> 0
C119: Investeringen na afsluitdatum (afschrijvingstabel) | K119: MVA volgens balans afsluitdatum
C120: Totaal aanschafwaarde | D120: =D112+D33+D118+D119 -> 0 | L120: =L118-L119 -> 0
C121: Totaal volgens afschrijvingstabel
C122: Verschil (moet 0 zijn) | D122: =D120-D121 -> 0

Sheet Goodwill
A1: ='weerhouden waarde'!A1 -> [NAAM VENNOOTSCHAP]
A3: ='gecorrigeerd eigen vermogen'!A4 -> Toestand op [afsluitdatum] (afsluitdatum)
A5: WAARDERING GOODWILL
B7: Gecorrigeerd eigen vermogen | D7: =ROUND('gecorrigeerd eigen vermogen'!E44,-3) -> 0
B9: Overtollige activa (3) | D9: =-E42 -> 0
B11: Geïnvesteerd risicokapitaal | D11: =D7+D9 -> 0
B12: Afgerond | D12: =IF(D11>0,CEILING(D11,1000),0) -> 0
B14: Gecorrigeerde vrije cash flow | D14: ='Gecorrigeerde vrije cash flow'!K76 -> 0
B16: vereist rendement op EV (1) | C16: =E31 -> 0
B17: aantal jaar goodwill (2) | C17: 7 | D17: jaar
B18: vereist risicoloos rendement (gemiddelde OLO 20 jaar + 1,5%) | C18: =+OLO!G49+1.5% -> 0.04269
B21: goodwill | D21: =(D14-D12*C16)/(C18+(100/C17)%) -> 0
B22: afgerond | D22: =ROUND(D21,-3) -> 0
A25: Het rendement op EV wordt bepaald op basis van de samenstelling van het actief :
B26: - O&O : | C26: 0.2 | D26: =E54 -> 0 | E26: =C26*D26 -> 0
B27: - materiële vaste activa : | C27: 0.12 | D27: =E55+E56 -> 0 | E27: =C27*D27 -> 0
B28: - voorraad : | C28: 0.1 | D28: =E59 -> 0 | E28: =C28*D28 -> 0
B29: - vorderingen : | C29: 0.08 | D29: =E67 -> 0 | E29: =C29*D29 -> 0
B30: - liquide middelen : | C30: 0.06 | D30: =E71 -> 0 | E30: =C30*D30 -> 0
D31: =SUM(D26:D30) -> 0 | E31: =SUM(E26:E30) -> 0
A33: 7 jaar wordt weerhouden omwille van :
B34: a) [motivering +] (+)
B35: b) [motivering +] (+)
B36: c) [motivering +] (+)
B37: d) [motivering +] (+)
B38: e) [motivering -] (-)
B39: f) [motivering -] (-)
A42: (3) Overtollige activa en passiva worden als volgt berekend (toestand per [afsluitdatum]): | E42: =SUM(D43:D49) -> 0
B44: Roerend vermogen
B45: Liquide middelen | D45: =D71 -> 0
B46: Terug te vorderen belastingen
B47: Te betalen vennootschapsbelasting
B48: R/C bestuurder
B49: Correctie financiering werkkapitaal | D49: =E118 -> 0 | E49: (*)
B51: BALANS | C51: CODE | D51: [afsluitdatum]
A53: 1. | B53: OPRICHTINGSKOSTEN | C53: 20
A54: 2. | B54: IMMATERIELE VASTE ACTIVA | C54: 21 | E54: =IFERROR(D54/D74,0) -> 0
A55: 3. | B55: MATERIELE VASTE ACTIVA | C55: 22/27 | E55: =IFERROR(D55/D74,0) -> 0
A56: 4. | B56: FINANCIELE VASTE ACTIVA | C56: 28 | E56: =IFERROR(D56/D74,0) -> 0
A57: 5. | B57: VORDERINGEN OP + 1 JAAR | C57: 29
A58: 6. | B58: VOORRADEN EN BESTELLINGEN IN UITVOERING | C58: 3 | D58: =D59+D66 -> 0
B59: A. VOORRADEN | C59: 30/36 | D59: =SUM(D60:D66) -> 0 | E59: =IFERROR(D58/D74,0) -> 0
B60: Grond- en hulpstoffen | C60: 30/31
B61: Goederen in bewerking | C61: 32
B62: Gereed produkt | C62: 33
B63: Handelsgoederen | C63: 34 | E63: =IFERROR(D63/D74,0) -> 0
B64: Onroerende goederen voor verkoop | C64: 35
B65: Vooruitbetalingen | C65: 36
B66: B. BESTELLINGEN IN UITVOERING | C66: 37
A67: 7. | B67: VORDERINGEN OP -1JAAR | C67: 40/41 | D67: =SUM(D68:D69) -> 0 | E67: =IFERROR((D67+D57)/D74,0) -> 0
B68: A. HANDELSVORDERINGEN | C68: 40
B69: B. OVERIGE VORDERINGEN | C69: 41
A70: 8. | B70: GELDBELEGGINGEN | C70: 50/53
A71: 9. | B71: LIQUIDE MIDDELEN | C71: 54/58 | E71: =IFERROR((D70+D71+D72)/D74,0) -> 0
A72: 10. | B72: OVERLOPENDE REKENINGEN | C72: 490/1
B74: A C T I V A | C74: 20/58 | D74: =D55+D56+D58+D67+D71+D72+D70+D57+D54+D53 -> 0
A77: (3a) | B77: [rekening - omschrijving lening (LT/KT)]
C83: =SUM(C77:C82) -> 0
A85: (3b) | B85: Normalisatie werkkapitaal
B86: Vlottende activa (exclusief overtollig) | C86: =D58+D67+D72 -> 0
B87: Vreemd vermogen korte termijn (exclusief overtollig)
C88: =C86+C87 -> 0
B90: (*) Correctie financiering werkkapitaal
B91: Op basis van onderstaand overzicht bedraagt de solvabiliteit van de onderneming [x]%. [Motivering al dan niet weerhouden van een theoretische financiering van het werkkapitaal.]
B99: Voorraad
B100: Klantentegoed
B101: Overige vorderingen
B102: Overlopende rekeningen actief
B103: Straight loans
B104: Financiering vakantiegeld
B105: Handelsschulden
B106: Te betalen BTW
B107: Te betalen sociale schulden
B108: Overlopende rekeningen passief
B109: Werkkapitaal | D109: =SUM(D99:D108) -> 0 | E109: =SUM(E99:E108) -> 0
B110: Omzet (12m) | D110: ='Gecorrigeerde vrije cash flow'!K12 -> 0 | E110: ='Gecorrigeerde vrije cash flow'!N12 -> 0
B111: % | D111: =IFERROR(D109/D110,0) -> 0 | E111: =IFERROR(E109/E110,0) -> 0
B113: Eigen vermogen (excl. HWMW)
B114: Totaal vermogen
B116: Solvabiliteit | D116: =IFERROR(D113/D114,0) -> 0 | E116: =IFERROR(E113/E114,0) -> 0
B118: Correctie financiering werkkapitaal | E118: 0
B120: Solvabiliteit na correctie | E120: =IFERROR((E113-E118)/E114,0) -> 0
I125: MVA | J125: =ROUND(D55/1000,0) -> 0
I126: Voorraad | J126: =ROUND(D58/1000,0) -> 0
I127: Vorderingen | J127: =ROUND((D57+D67)/1000,0) -> 0
I128: Overlopend | J128: =ROUND(D72/1000,0) -> 0
I129: Cash | J129: =ROUND((D70+D71)/1000,0) -> 0
I130: Overige | J130: =ROUND((D53+D54+D56)/1000,0) -> 0
J131: =SUM(J125:J130) -> 0
I133: Inbreng
I134: Reserves + overgedragen | K134: =IFERROR(SUM(J133:J134)/J131,0) -> 0
I135: Leningen | J135: =ROUND(C83/1000,0) -> 0
I136: R/C | J136: =ROUND(-D48/1000,0) -> 0
I137: Lev + fisc/soc
I138: Overlopend | K138: =IFERROR(SUM(J135:J138)/J131,0) -> 0
J139: =SUM(J133:J138) -> 0

Sheet Gecorrigeerde vrije cash flow
B1: ='gecorrigeerd eigen vermogen'!A1 -> [NAAM VENNOOTSCHAP]
B4: ='gecorrigeerd eigen vermogen'!A4 -> Toestand op [afsluitdatum] (afsluitdatum)
B7: GECORRIGEERDE VRIJE CASH FLOW | R7: Prognose
H10: (12 maanden) | K10: (12 maanden) | N10: (12 maanden) | R10: (12 maanden)
B11: Normalisatiefactor (12 / aantal maanden) | H11: 1 | K11: 1 | N11: 1 | R11: 1
B12: Omzet | H12: =SUM(H13:H18) -> 0 | K12: =SUM(K13:K18) -> 0 | N12: =SUM(N13:N18) -> 0 | R12: =SUM(R13:R18) -> 0
B13: Verkopen | I13: =IFERROR(H13/H$12,"") | L13: =IFERROR(K13/K$12,"") | O13: =IFERROR(N13/N$12,"") | S13: =IFERROR(R13/R$12,"")
B14: Export | I14: =IFERROR(H14/H$12,"") | L14: =IFERROR(K14/K$12,"") | O14: =IFERROR(N14/N$12,"") | S14: =IFERROR(R14/R$12,"")
B15: Commissie | I15: =IFERROR(H15/H$12,"") | L15: =IFERROR(K15/K$12,"") | O15: =IFERROR(N15/N$12,"") | S15: =IFERROR(R15/R$12,"")
B16: Cardetailing | I16: =IFERROR(H16/H$12,"") | L16: =IFERROR(K16/K$12,"") | O16: =IFERROR(N16/N$12,"") | S16: =IFERROR(R16/R$12,"")
B17: Verhuur | I17: =IFERROR(H17/H$12,"") | L17: =IFERROR(K17/K$12,"") | O17: =IFERROR(N17/N$12,"") | S17: =IFERROR(R17/R$12,"")
B18: Doorrekening | I18: =IFERROR(H18/H$12,"") | L18: =IFERROR(K18/K$12,"") | O18: =IFERROR(N18/N$12,"") | S18: =IFERROR(R18/R$12,"")
I19: =IFERROR(H19/H$12,"") | L19: =IFERROR(K19/K$12,"") | O19: =IFERROR(N19/N$12,"") | S19: =IFERROR(R19/R$12,"")
B20: - Aankopen | H20: =-SUM(H21:H24) -> 0 | I20: =IFERROR(H20/H$12,"") | K20: =-SUM(K21:K24) -> 0 | L20: =IFERROR(K20/K$12,"") | N20: =-SUM(N21:N24) -> 0 | O20: =IFERROR(N20/N$12,"") | R20: =-SUM(R21:R24) -> 0 | S20: =IFERROR(R20/R$12,"")
B21: Aankopen | I21: =IFERROR(-H21/H$20,"") | L21: =IFERROR(-K21/K$20,"") | O21: =IFERROR(-N21/N$20,"") | S21: =IFERROR(-R21/R$20,"")
B22: Onderaanneming | I22: =IFERROR(-H22/H$20,"") | L22: =IFERROR(-K22/K$20,"") | O22: =IFERROR(-N22/N$20,"") | S22: =IFERROR(-R22/R$20,"")
B23: Leasingkosten | I23: =IFERROR(-H23/H$20,"") | L23: =IFERROR(-K23/K$20,"") | O23: =IFERROR(-N23/N$20,"") | S23: =IFERROR(-R23/R$20,"")
B24: Vooraadwijziging (+/-) | I24: =IFERROR(-H24/H$20,"") | L24: =IFERROR(-K24/K$20,"") | O24: =IFERROR(-N24/N$20,"") | S24: =IFERROR(-R24/R$20,"")
B26: = Bruto marge | H26: =H12+H20 -> 0 | I26: =IFERROR(H26/H$12,"") | K26: =K12+K20 -> 0 | L26: =IFERROR(K26/K$12,"") | N26: =N12+N20 -> 0 | O26: =IFERROR(N26/N$12,"") | R26: =R12+R20 -> 0 | S26: =IFERROR(R26/R$12,"")
B28: - Transportkosten | I28: =IFERROR(H28/H$12,"") | L28: =IFERROR(K28/K$12,"") | O28: =IFERROR(N28/N$12,"") | S28: =IFERROR(R28/R$12,"")
B30: = Contributiemarge | H30: =H26+H28 -> 0 | I30: =IFERROR(H30/H$12,"") | K30: =K26+K28 -> 0 | L30: =IFERROR(K30/K$12,"") | N30: =N26+N28 -> 0 | O30: =IFERROR(N30/N$12,"") | R30: =R26+R28 -> 0 | S30: =IFERROR(R30/R$12,"")
B32: - Diensten en diverse goederen | H32: =SUM(H33:H39) -> 0 | I32: =IFERROR(H32/H$12,"") | K32: =SUM(K33:K39) -> 0 | L32: =IFERROR(K32/K$12,"") | N32: =SUM(N33:N39) -> 0 | O32: =IFERROR(N32/N$12,"") | R32: =SUM(R33:R39) -> 0 | S32: =IFERROR(R32/R$12,"")
B33: Huur (610) | I33: =IFERROR(H33/H$32,"") | L33: =IFERROR(K33/K$32,"") | O33: =IFERROR(N33/N$32,"") | S33: =IFERROR(R33/R$32,"")
B34: Kosten gebouw (611) | I34: =IFERROR(H34/H$32,"") | L34: =IFERROR(K34/K$32,"") | O34: =IFERROR(N34/N$32,"") | S34: =IFERROR(R34/R$32,"")
B35: Kantoor & informatica (612) | I35: =IFERROR(H35/H$32,"") | L35: =IFERROR(K35/K$32,"") | O35: =IFERROR(N35/N$32,"") | S35: =IFERROR(R35/R$32,"")
B36: Kosten wagenpark (613) | I36: =IFERROR(H36/H$32,"") | L36: =IFERROR(K36/K$32,"") | O36: =IFERROR(N36/N$32,"") | S36: =IFERROR(R36/R$32,"")
B37: Marketing (614) | I37: =IFERROR(H37/H$32,"") | L37: =IFERROR(K37/K$32,"") | O37: =IFERROR(N37/N$32,"") | S37: =IFERROR(R37/R$32,"")
B38: Overige (615) | I38: =IFERROR(H38/H$32,"") | L38: =IFERROR(K38/K$32,"") | O38: =IFERROR(N38/N$32,"") | S38: =IFERROR(R38/R$32,"")
B39: Bezoldiging bedrijfsleiders | I39: =IFERROR(H39/H$32,"") | L39: =IFERROR(K39/K$32,"") | O39: =IFERROR(N39/N$32,"") | S39: =IFERROR(R39/R$32,"")
B41: - Personeelskosten (incl. interims) | I41: =IFERROR(H41/H$12,"") | L41: =IFERROR(K41/K$12,"") | O41: =IFERROR(N41/N$12,"") | S41: =IFERROR(R41/R$12,"")
B43: + Overige bedrijfsopbrengsten | I43: =IFERROR(H43/H$12,"") | L43: =IFERROR(K43/K$12,"") | O43: =IFERROR(N43/N$12,"") | S43: =IFERROR(R43/R$12,"")
B45: - Overige bedrijfskosten | I45: =IFERROR(H45/H$12,"") | L45: =IFERROR(K45/K$12,"") | O45: =IFERROR(N45/N$12,"") | S45: =IFERROR(R45/R$12,"")
B47: + Financiële operationele opbrengsten | I47: =IFERROR(H47/H$12,"") | L47: =IFERROR(K47/K$12,"") | O47: =IFERROR(N47/N$12,"") | S47: =IFERROR(R47/R$12,"")
B48: - Opbrengsten beschikbare waarden (6) | I48: =IFERROR(H48/H$12,"") | L48: =IFERROR(K48/K$12,"") | O48: =IFERROR(N48/N$12,"") | S48: =IFERROR(R48/R$12,"")
B49: - Financiële operationele kosten | I49: =IFERROR(H49/H$12,"") | L49: =IFERROR(K49/K$12,"") | O49: =IFERROR(N49/N$12,"") | S49: =IFERROR(R49/R$12,"")
B50: - Intresten op RC/net debt (5) | I50: =IFERROR(H50/H$12,"") | L50: =IFERROR(K50/K$12,"") | O50: =IFERROR(N50/N$12,"") | S50: =IFERROR(R50/R$12,"")
B52: - Normalisaties (operationeel) (1) | H52: =H90+H104+H115 -> 0 | I52: =IFERROR(H52/H$12,"") | K52: =K90+K104+K115 -> 0 | L52: =IFERROR(K52/K$12,"") | N52: =N90+N104+N115 -> 0 | O52: =IFERROR(N52/N$12,"") | R52: =R90+R104+R115 -> 0 | S52: =IFERROR(R52/R$12,"")
V53: controle | W53: controle | X53: controle
B54: = EBITDA | H54: =H30+H32+H41+H43+H45+H47+H49+H52 -> 0 | I54: =IFERROR(H54/H$12,"") | K54: =K30+K32+K41+K43+K45+K47+K49+K52 -> 0 | L54: =IFERROR(K54/K$12,"") | N54: =N30+N32+N41+N43+N45+N47+N49+N52 -> 0 | O54: =IFERROR(N54/N$12,"") | R54: =R30+R32+R41+R43+R45+R47+R49+R52 -> 0 | S54: =IFERROR(R54/R$12,"") | V54: =H54-H52-H49-H47 -> 0 | W54: =K54-K52-K49-K47 -> 0 | X54: =N54-N52-N49-N47 -> 0
B55: weerhouden EBITDA | K55: =ROUND(H54*H74+K54*K74+N54*N74+R54*R74,-3) -> 0
B57: - Vervangingsinvesteringen (2) | H57: =-MVA!N112 -> 0 | I57: =IFERROR(H57/H$12,"") | K57: =-MVA!N112 -> 0 | L57: =IFERROR(K57/K$12,"") | N57: =-MVA!N112 -> 0 | O57: =IFERROR(N57/N$12,"") | R57: =-MVA!N112 -> 0 | S57: =IFERROR(R57/R$12,"") | V57: =V54-V55-V56 -> 0 | W57: =W54-W55-W56 -> 0 | X57: =X54-X55-X56 -> 0
V58: =IF(ABS(V57)<0.01,"OK","FOUT") -> OK | W58: =IF(ABS(W57)<0.01,"OK","FOUT") -> OK | X58: =IF(ABS(X57)<0.01,"OK","FOUT") -> OK
B59: = EBIT | H59: =H54+H57 -> 0 | I59: =IFERROR(H59/H$12,"") | K59: =K54+K57 -> 0 | L59: =IFERROR(K59/K$12,"") | N59: =N54+N57 -> 0 | O59: =IFERROR(N59/N$12,"") | R59: =R54+R57 -> 0 | S59: =IFERROR(R59/R$12,"")
B62: + Financiële opbrengsten | I62: =IFERROR(H62/H$12,"") | L62: =IFERROR(K62/K$12,"") | O62: =IFERROR(N62/N$12,"") | S62: =IFERROR(R62/R$12,"")
B63: - Financiële kosten | I63: =IFERROR(H63/H$12,"") | L63: =IFERROR(K63/K$12,"") | O63: =IFERROR(N63/N$12,"") | S63: =IFERROR(R63/R$12,"")
B65: - Normalisaties (financieel) (3) | H65: =-Goodwill!$E$118*4% -> 0 | I65: =IFERROR(H65/H$12,"") | K65: =-Goodwill!$E$118*4% -> 0 | L65: =IFERROR(K65/K$12,"") | N65: =-Goodwill!$E$118*4% -> 0 | O65: =IFERROR(N65/N$12,"") | R65: =-Goodwill!$E$118*4% -> 0 | S65: =IFERROR(R65/R$12,"")
B67: = Vrije cash flow vóór belastingen | H67: =SUM(H59:H66) -> 0 | I67: =IFERROR(H67/H$12,"") | K67: =SUM(K59:K66) -> 0 | L67: =IFERROR(K67/K$12,"") | N67: =SUM(N59:N66) -> 0 | O67: =IFERROR(N67/N$12,"") | R67: =SUM(R59:R66) -> 0 | S67: =IFERROR(R67/R$12,"")
B68: weerhouden FCF | K68: =ROUND(H67*H74+K67*K74+N67*N74+R67*R74,-3) -> 0
B70: - Belastingen (25%) | H70: =IF(H67>0,-H67*0.25,0) -> 0 | I70: =IFERROR(H70/H$12,"") | K70: =IF(K67>0,-K67*0.25,0) -> 0 | L70: =IFERROR(K70/K$12,"") | N70: =IF(N67>0,-N67*0.25,0) -> 0 | O70: =IFERROR(N70/N$12,"") | R70: =IF(R67>0,-R67*0.25,0) -> 0 | S70: =IFERROR(R70/R$12,"")
B72: = Vrije Cash Flow na belastingen | H72: =H67+H70 -> 0 | I72: =IFERROR(H72/H$12,"") | K72: =K67+K70 -> 0 | L72: =IFERROR(K72/K$12,"") | N72: =N67+N70 -> 0 | O72: =IFERROR(N72/N$12,"") | R72: =R67+R70 -> 0 | S72: =IFERROR(R72/R$12,"")
B74: Wegingsfactor (4) | H74: 0 | K74: 0 | N74: 0 | R74: 0
B76: Weerhouden FCF na belastingen | H76: afgerond : | K76: =ROUND(H72*H74+K72*K74+N72*N74+R72*R74,-3) -> 0
B79: (1) Navolgende operationele normalisaties worden doorgevoerd :
B81: a) Normalisatie bestuurdersvergoeding
B82: [Marktconforme bestuurdersvergoeding van ... EUR (totale kost) voor ... fulltime bestuurder(s), ter vervanging van de huidige bezoldiging (618) - of: geen normalisatie.]
B85: 618... - Bezoldiging bestuurder
B86: 618... - Voordelen alle aard
B87: 618... - Overige
H88: =SUM(H85:H87) -> 0 | K88: =SUM(K85:K87) -> 0 | N88: =SUM(N85:N87) -> 0 | R88: =SUM(R85:R87) -> 0
B90: Normalisatie | H90: =IF(H92="",0,H92-H88) -> 0 | K90: =IF(K92="",0,K92-K88) -> 0 | N90: =IF(N92="",0,N92-N88) -> 0 | R90: =IF(R92="",0,R92-R88) -> 0
B92: Genormaliseerde vergoeding (invoer)
B94: b) Vervangingshuur
B95: [Huursituatie: eigenaar van het pand / huur van verbonden partij met marktconforme huur van ... / huur van derde partij (reële huur weerhouden).]
B101: 610... - Huur
H102: =SUM(H101:H101) -> 0 | K102: =SUM(K101:K101) -> 0 | N102: =SUM(N101:N101) -> 0 | R102: =SUM(R101:R101) -> 0
B104: Normalisatie | H104: =IF(H106="",0,H106-H102) -> 0 | K104: =IF(K106="",0,K106-K102) -> 0 | N104: =IF(N106="",0,N106-N102) -> 0 | R104: =IF(R106="",0,R106-R102) -> 0
B106: Marktconforme huur (invoer)
B111: c) Normalisatie kosten
B112: [Te normaliseren kosten of: Er worden geen kosten genormaliseerd.]
B114: [rekening - omschrijving]
H115: =SUM(H114:H114) -> 0 | K115: =SUM(K114:K114) -> 0 | N115: =SUM(N114:N114) -> 0 | R115: =SUM(R114:R114) -> 0
B133: (2) Vervangingsinvesteringen :
B134: De vervangingsinvesteringen werden bepaald op basis van de aanschaffingswaarde van de activa vermeld op de afschrijvingstabel na aftrek van een eventuele restwaarde en economische gebruiksduur afhankelijk van het type activa (zie afzonderlijke berekening).
B137: (3) Normalisaties financieel :
B138: [Correctie voor een fictieve financiering van het werkkapitaal (zie goodwill, 4% op het bedrag in Goodwill!E118) en eventuele andere financiële normalisaties, bv. intrest op de R/C bestuurder.]
B141: (4) Wegingscoefficiënt
B142: [Motivering van de weging van de boekjaren en de prognose.]

Sheet OLO
A1: ='Gecorrigeerde vrije cash flow'!B1 -> [NAAM VENNOOTSCHAP]
A4: Berekeningstabel inflatievoet en OLO
A7: Bron:
A9: - Inflatie (historisch) : | C9: https://nl.inflation.eu/inflatiecijfers/belgie/historische-inflatie/cpi-inflatie-
C10: belgie.aspx
A11: - Inflatie (toekomst) : | C11: https://www.plan.be/databases/17-nl-indexcijfer+der+consumptieprijzen
C12: +inflatievooruitzichten
A13: - OLO (historisch) : | C13: http://stat.nbb.be/Index.aspx?DataSetCode=IRTRCERT&lang=nl
A14: - OLO (toekomst) : | C14: geen gegevens beschikbaar
A16: Gegevens :
A18: Jaar | D18: Inflatie | F18: OLO rentevoet
F19: 10 jaar | G19: 20 jaar | H19: 30 jaar
A21: 24 | B21: 2001 | D21: 0.0247 | F21: 0.0511 | G21: 0.056 | H21: 0.0568
A22: 23 | B22: 2002 | D22: 0.0165 | F22: 0.0498 | G22: 0.0535 | H22: 0.0538
A23: 22 | B23: 2003 | D23: 0.0159 | F23: 0.0417 | G23: 0.0479
A24: 21 | B24: 2004 | D24: 0.021 | F24: 0.0413 | G24: 0.0464
A25: 20 | B25: 2005 | D25: 0.0278 | F25: 0.0342 | G25: 0.0374 | H25: 0.039
A26: 19 | B26: 2006 | D26: 0.0179 | F26: 0.038 | G26: 0.0399 | H26: 0.0406
A27: 18 | B27: 2007 | D27: 0.0182 | F27: 0.0435 | G27: 0.0449 | H27: 0.0453
A28: 17 | B28: 2008 | D28: 0.0449 | F28: 0.0444 | G28: 0.0473 | H28: 0.0476
A29: 16 | B29: 2009 | D29: -0.0004 | F29: 0.0394 | G29: 0.0446 | H29: 0.0453
A30: 15 | B30: 2010 | D30: 0.0219 | F30: 0.0344 | G30: 0.0395 | H30: 0.0409
A31: 14 | B31: 2011 | D31: 0.0353 | F31: 0.042 | G31: 0.0458 | H31: 0.0467
A32: 13 | B32: 2012 | D32: 0.0284 | F32: 0.0298 | G32: 0.0358 | H32: 0.0366
A33: 12 | B33: 2013 | D33: 0.0111 | F33: 0.0243 | G33: 0.0318 | H33: 0.0337
A34: 11 | B34: 2014 | D34: 0.0034 | F34: 0.0172 | G34: 0.0247 | H34: 0.0275
A35: 10 | B35: 2015 | D35: 0.0056 | F35: 0.0086 | G35: 0.0152 | H35: 0.0169
A36: 9 | B36: 2016 | D36: 0.0197 | F36: 0.0049 | G36: 0.0114 | H36: 0.0142
... A44: 1 | B44: 2024 | D44: 0.0314 | F44: 0.0291 | G44: 0.0337 | H44: 0.0345
A45: 0 | B45: 2025 | D45: 0.0255 | G45: 0.0386
A47: Gemiddelde laatste 10 jaar | D47: =AVERAGE(D36:D45) -> 0.03015 | F47: =AVERAGE(F35:F44) -> 0.0107 | G47: =AVERAGE(G36:G45) -> 0.01843 | H47: =AVERAGE(H35:H44) -> 0.01818
A48: Gemiddelde laatste 10 jaar + T | D48: =AVERAGE(D35:D45) -> 0.027918182
A49: Gemiddelde laatste 20 jaar | D49: =AVERAGE(D26:D45) -> 0.02439 | F49: =AVERAGE(F25:F44) -> 0.02271 | G49: =AVERAGE(G26:G45) -> 0.02769 | H49: =AVERAGE(H25:H44) -> 0.02925
A50: Gemiddelde laatste 20 jaar + T | D50: =AVERAGE(D25:D45) -> 0.024552381

Sheet Rendementswaarde
A1: ='Gecorrigeerde vrije cash flow'!B1 -> [NAAM VENNOOTSCHAP]
A4: ='gecorrigeerd eigen vermogen'!A4 -> Toestand op [afsluitdatum] (afsluitdatum)
A7: RENDEMENTSWAARDE
A9: (gemiddelde van methode 1 en methode 2)
A12: rendementswaarde methode 1 | C12: ='rendementswaarde 1'!C19 -> 0
A13: rendementswaarde methode 2 | C13: ='rendementswaarde 2'!G44 -> 0
A15: rendementswaarde | C15: =ROUNDUP((C12+C13)/2,-4) -> 0

Sheet rendementswaarde 1
A1: =Rendementswaarde!A1 -> [NAAM VENNOOTSCHAP]
A4: ='gecorrigeerd eigen vermogen'!A4 -> Toestand op [afsluitdatum] (afsluitdatum)
A7: RENDEMENTSWAARDE METHODE 1
A10: gecorrigeerde vrije cash flow | C10: ='Gecorrigeerde vrije cash flow'!K76 -> 0
A11: rendementseis op geïnvesteerd vermogen | C11: =Goodwill!C16+4% -> 0.04 | F11: =IFERROR(C13/C10,0) -> 0 | G11: equity multiple
A12: (cf. berekening goodwill + 4% risicopremie)
C13: =C10/C11 -> 0
A15: + overtollig vermogen | C15: =Goodwill!E42 -> 0
A18: rendementswaarde | C18: =+C13+C15 -> 0
A19: afgerond | C19: =ROUNDUP(C18,-3) -> 0

Sheet rendementswaarde 2
A1: ='rendementswaarde 1'!A1 -> [NAAM VENNOOTSCHAP]
A4: ='gecorrigeerd eigen vermogen'!A4 -> Toestand op [afsluitdatum] (afsluitdatum)
A7: RENDEMENTSWAARDE METHODE 2
A10: genormaliseerde vrije cash flow | E10: ='Gecorrigeerde vrije cash flow'!K76 -> 0
A12: Terugverdienperiode | E12: 7 | F12: jaar
B14: vrije cash flow vóór belastingen | E14: ='Gecorrigeerde vrije cash flow'!K68 -> 0
B15: normale interest voor financiering | E15: =Goodwill!C18-1% -> 0.03269 | F15: (OLO 20jaar)
B16: te ontlenen kapitaal met cash flow | E16: =G29 -> 0
B17: afgerond | E17: =ROUND((1-$F$20)*E12*E14/(1+(1-$F$20)*E15*E12/2),2) -> 0 | F17: EUR
C19: kapitaal | D19: interest | E19: winst voor | F19: belasting | G19: winst na
E20: belasting | F20: 0.25 | G20: belasting
B22: jaar 1 | C22: =E17 -> 0 | D22: =(C22+C23)/2*$E$15 -> 0 | E22: =$E$14-D22 -> 0 | F22: =-E22*25% -> 0 | G22: =E22+F22 -> 0
B23: jaar 2 | C23: =C22-$C$22/$E$12 -> 0 | D23: =(C23+C24)/2*$E$15 -> 0 | E23: =$E$14-D23 -> 0 | F23: =-E23*25% -> 0 | G23: =E23+F23 -> 0
B24: jaar 3 | C24: =C23-$C$22/$E$12 -> 0 | D24: =(C24+C25)/2*$E$15 -> 0 | E24: =$E$14-D24 -> 0 | F24: =-E24*25% -> 0 | G24: =E24+F24 -> 0
B25: jaar 4 | C25: =C24-$C$22/$E$12 -> 0 | D25: =(C25+C26)/2*$E$15 -> 0 | E25: =$E$14-D25 -> 0 | F25: =-E25*25% -> 0 | G25: =E25+F25 -> 0
B26: jaar 5 | C26: =C25-$C$22/$E$12 -> 0 | D26: =(C26+C27)/2*$E$15 -> 0 | E26: =$E$14-D26 -> 0 | F26: =-E26*25% -> 0 | G26: =E26+F26 -> 0
B27: jaar 6 | C27: =C26-$C$22/$E$12 -> 0 | D27: =(C27+C28)/2*$E$15 -> 0 | E27: =$E$14-D27 -> 0 | F27: =-E27*25% -> 0 | G27: =E27+F27 -> 0
B28: jaar 7 | C28: =C27-$C$22/$E$12 -> 0 | D28: =(C28+C29)/2*$E$15 -> 0 | E28: =$E$14-D28 -> 0 | F28: =-E28*25% -> 0 | G28: =E28+F28 -> 0
G29: =SUM(G22:G28) -> 0
B31: gecorrigeerd eigen vermogen | E31: =ROUND('gecorrigeerd eigen vermogen'!E44,-3) -> 0
B32: sociaal passief (1) | E32: 0
B33: extra liquidatiebelasting | E33: 0
B34: vennootschapsbelasting (25 %) | E34: =-(25%-'gecorrigeerd eigen vermogen'!C26)*'gecorrigeerd eigen vermogen'!D25 -> 0
B35: liquidatiebelasting (0%) | E35: =(-'gecorrigeerd eigen vermogen'!D38*0%)-'gecorrigeerd eigen vermogen'!E33 -> 0
E36: =SUM(E31:E35) -> 0
B37: actualisatievoet (2) | E37: =J74 -> 0.04269
E38: =E36/((1+E37)^E12) -> 0
B40: te ontlenen kapitaal met cash flow | G40: =+E17 -> 0
B41: gecorrigeerd eigen vermogen bij onmiddellijke liquidatie | G41: =ROUND(E38,-3) -> 0
A43: rendementswaarde methode 2 | G43: =SUM(G40:G42) -> 0
A44: afgerond | G44: =ROUND(G43,-3) -> 0
A49: (1) Sociaal passief :
B51: Het betreft zowel bedienden als arbeiders. In het kader van de overgang naar het eenheidsstatuut
B52: wordt voor zowel de bedienden als de arbeiders rekening gehouden met een gemiddelde opzeg-
B53: termijn van 2 maand.
B55: Bezoldiging arbeiders + bedienden | D55: =-'Gecorrigeerde vrije cash flow'!N41 -> 0 | E55: code 620/621
B56: aantal maanden | D56: 1/6
B57: Sociaal passief | D57: =D55/6 -> 0
B58: Belastingsvoet | D58: 0.25
B59: Weerhouden sociaal passief | D59: =D57*(1-D58) -> 0
B61: Arbeiders:
B63: Bezoldiging arbeiders | D63: 0
B64: Aantal maanden | D64: 1/6
B65: Sociaal passief | D65: =D63/6 -> 0
B66: Belastingsvoet | D66: 0.3
B67: Weerhouden sociaal passief | D67: =D65*(1-D66) -> 0
B69: Totale kost sociaal passief | D69: =D59+D67 -> 0
A72: (2) Er wordt rekening gehouden met een actualisatievoet van | E72: =+Goodwill!C18 -> 0.04269 | F72: vereist risicoloos rendement (OLO 20 jaar + 1,5%)
F74: excess vermogen | H74: =Goodwill!E42 -> 0 | J74: =IF(H75=0,E72,E72-(E72*(H74/H75))) -> 0.04269
F75: gecorrigeerd eigen vermogen | H75: ='gecorrigeerd eigen vermogen'!E44 -> 0

Sheet Marktwaarde 
A1: ='rendementswaarde 2'!A1 -> [NAAM VENNOOTSCHAP]
A4: ='weerhouden waarde'!A6 -> Toestand op [afsluitdatum] (afsluitdatum)
A7: MARKTWAARDE OBV EBITDA
B10: Waarde | C10: Weging | D10: Weerhouden
A12: =IF('Gecorrigeerde vrije cash flow'!R9="","EBITDA boekjaar","EBITDA boekjaar "&YEAR('Gecorrigeerde vrije cash flow'!R9)&" (prognose)") -> EBITDA boekjaar | B12: ='Gecorrigeerde vrije cash flow'!R54 -> 0 | C12: ='Gecorrigeerde vrije cash flow'!R74 -> 0 | D12: =B12*C12 -> 0
A13: =IF('Gecorrigeerde vrije cash flow'!N9="","EBITDA boekjaar","EBITDA boekjaar "&YEAR('Gecorrigeerde vrije cash flow'!N9)&"") -> EBITDA boekjaar | B13: ='Gecorrigeerde vrije cash flow'!N54 -> 0 | C13: ='Gecorrigeerde vrije cash flow'!N74 -> 0 | D13: =B13*C13 -> 0
A14: =IF('Gecorrigeerde vrije cash flow'!K9="","EBITDA boekjaar","EBITDA boekjaar "&YEAR('Gecorrigeerde vrije cash flow'!K9)&"") -> EBITDA boekjaar | B14: ='Gecorrigeerde vrije cash flow'!K54 -> 0 | C14: ='Gecorrigeerde vrije cash flow'!K74 -> 0 | D14: =B14*C14 -> 0
A15: =IF('Gecorrigeerde vrije cash flow'!H9="","EBITDA boekjaar","EBITDA boekjaar "&YEAR('Gecorrigeerde vrije cash flow'!H9)&"") -> EBITDA boekjaar | B15: ='Gecorrigeerde vrije cash flow'!H54 -> 0 | C15: ='Gecorrigeerde vrije cash flow'!H74 -> 0 | D15: =B15*C15 -> 0
A17: Gewogen gemiddelde EBITDA (afgerond) | D17: =ROUND(SUM(D12:D15),-2) -> 0
A19: Weerhouden multiplicator obv VLERICK M&A Monitor [jaar] ([sector])
A21: Ondernemingswaarde | D21: =D17*D19 -> 0
A23: + aanvullende activa (cash + RC) / - net debt | D23: =Goodwill!E42 -> 0
A24: - debt (1) | D24: =-Goodwill!C83 -> 0
A26: Marktwaarde obv EBITDA | D26: =+D21+D23+D24 -> 0
A27: afgerond | D27: =ROUND(D26,-3) -> 0
